{"cameraMode":{"drawMode":0,"name":"Shaded","section":"Shading Mode"},"sceneLighting":true,"audioPlay":false,"sceneViewState":{"m_AlwaysRefresh":false,"showFog":true,"showSkybox":true,"showFlares":true,"showImageEffects":true,"showParticleSystems":true,"showVisualEffectGraphs":true,"m_FxEnabled":true},"in2DMode":false,"pivot":{"x":330.2537536621094,"y":2.1592154502868654,"z":29.01685905456543},"rotation":{"x":-0.11402188241481781,"y":-0.02740667201578617,"z":0.0031093484722077848,"w":-0.9931266903877258},"size":0.003581784898415208,"orthographic":false}